capitalcom/__init__.py
capitalcom/client.py
capitalcom/client_demo 2.py
capitalcom/client_demo.py
capitalcom/config.py
capitalcom/note.py
capitalcom/tests.py
capitalcom_python-0.2.1.dist-info/LICENSE
capitalcom_python-0.2.1.dist-info/METADATA
capitalcom_python-0.2.1.dist-info/WHEEL
capitalcom_python-0.2.1.dist-info/top_level.txt
capitalcom_python-0.2.1.dist-info/RECORD
